client/__init__.py
client/client_db.py
client/client_v1.py
client/decorate.py
client/metaclasses.py
client/port_descriptor.py
client/Client/__init__.py
client/Client/add_contact.py
client/Client/client.py
client/Client/del_contact.py
client/Client/main_win.py
client/Client/main_win_conv.py
client/Client/sendler.py
client/Client/start_user.py
client/log/__init__.py
client/log/client_log_config.py
client/log/server_log_config.py
client/unit_tests/__init__.py
client/unit_tests/test_client.py
client/unit_tests/test_for_test.py
client/unit_tests/test_server.py
sents_client_chat-1.0.dist-info/METADATA
sents_client_chat-1.0.dist-info/WHEEL
sents_client_chat-1.0.dist-info/top_level.txt
sents_client_chat-1.0.dist-info/RECORD
