Metadata-Version: 2.1
Name: sents-client-chat
Version: 1.0
Summary: Client packet
Author: Slav Senteryov
Author-email: ricar@mail.ru
